[{"code":"AM:Abovyan:1","name":"Abovyan","originalName":"Abovyan"},{"code":"AM:Agarak:1","name":"Agarak","originalName":"Agarak"},{"code":"AM:Agarakadzor:1","name":"Agarakadzor","originalName":"Agarakadzor"},{"code":"AM:Agarakavan:1","name":"Agarakavan","originalName":"Agarakavan"},{"code":"AM:Aghavnadzor:1","name":"Aghavnadzor","originalName":"Aghavnadzor"},{"code":"AM:Aghavnatun:1","name":"Aghavnatun","originalName":"Aghavnatun"},{"code":"AM:Akht’ala:1","name":"Akht’ala","originalName":"Akht’ala"},{"code":"AM:Akhuryan:1","name":"Akhuryan","originalName":"Akhuryan"},{"code":"AM:Aknalich:1","name":"Aknalich","originalName":"Aknalich"},{"code":"AM:Aknashen:1","name":"Aknashen","originalName":"Aknashen"},{"code":"AM:Akner:1","name":"Akner","originalName":"Akner"},{"code":"AM:Akunk’:1","name":"Akunk’","originalName":"Akunk’"},{"code":"AM:Alashkert:1","name":"Alashkert","originalName":"Alashkert"},{"code":"AM:Alaverdi:1","name":"Alaverdi","originalName":"Alaverdi"},{"code":"AM:Amasia:1","name":"Amasia","originalName":"Amasia"},{"code":"AM:Angeghakot’:1","name":"Angeghakot’","originalName":"Angeghakot’"},{"code":"AM:Anushavan:1","name":"Anushavan","originalName":"Anushavan"},{"code":"AM:Apaga:1","name":"Apaga","originalName":"Apaga"},{"code":"AM:Aparan:1","name":"Aparan","originalName":"Aparan"},{"code":"AM:Arabkir:1","name":"Arabkir","originalName":"Arabkir"},{"code":"AM:Aragats:1","name":"Aragats","originalName":"Aragats"},{"code":"AM:Arak’s:1","name":"Arak’s","originalName":"Arak’s"},{"code":"AM:Aralez:1","name":"Aralez","originalName":"Aralez"},{"code":"AM:Aramus:1","name":"Aramus","originalName":"Aramus"},{"code":"AM:Ararat:1","name":"Ararat","originalName":"Ararat"},{"code":"AM:Arazap’:1","name":"Arazap’","originalName":"Arazap’"},{"code":"AM:Arbat’:1","name":"Arbat’","originalName":"Arbat’"},{"code":"AM:Archis:1","name":"Archis","originalName":"Archis"},{"code":"AM:Areni:1","name":"Areni","originalName":"Areni"},{"code":"AM:Arevabuyr:1","name":"Arevabuyr","originalName":"Arevabuyr"},{"code":"AM:Arevashat:1","name":"Arevashat","originalName":"Arevashat"},{"code":"AM:Arevashogh:1","name":"Arevashogh","originalName":"Arevashogh"},{"code":"AM:Arevik:1","name":"Arevik","originalName":"Arevik"},{"code":"AM:Arevshat:1","name":"Arevshat","originalName":"Arevshat"},{"code":"AM:Argavand:1","name":"Argavand","originalName":"Argavand"},{"code":"AM:Argel:1","name":"Argel","originalName":"Argel"},{"code":"AM:Armash:1","name":"Armash","originalName":"Armash"},{"code":"AM:Armavir:1","name":"Armavir","originalName":"Armavir"},{"code":"AM:Arrap’i:1","name":"Arrap’i","originalName":"Arrap’i"},{"code":"AM:Arshaluys:1","name":"Arshaluys","originalName":"Arshaluys"},{"code":"AM:Artashat:1","name":"Artashat","originalName":"Artashat"},{"code":"AM:Arteni:1","name":"Arteni","originalName":"Arteni"},{"code":"AM:Artimet:1","name":"Artimet","originalName":"Artimet"},{"code":"AM:Artsvaberd:1","name":"Artsvaberd","originalName":"Artsvaberd"},{"code":"AM:Arzakan:1","name":"Arzakan","originalName":"Arzakan"},{"code":"AM:Arzni:1","name":"Arzni","originalName":"Arzni"},{"code":"AM:Ashnak:1","name":"Ashnak","originalName":"Ashnak"},{"code":"AM:Ashtarak:1","name":"Ashtarak","originalName":"Ashtarak"},{"code":"AM:Astghadzor:1","name":"Astghadzor","originalName":"Astghadzor"},{"code":"AM:Avshar:1","name":"Avshar","originalName":"Avshar"},{"code":"AM:Aygavan:1","name":"Aygavan","originalName":"Aygavan"},{"code":"AM:Aygehovit:1","name":"Aygehovit","originalName":"Aygehovit"},{"code":"AM:Aygek:1","name":"Aygek","originalName":"Aygek"},{"code":"AM:Aygepat:1","name":"Aygepat","originalName":"Aygepat"},{"code":"AM:Aygeshat:1","name":"Aygeshat","originalName":"Aygeshat"},{"code":"AM:Aygestan:1","name":"Aygestan","originalName":"Aygestan"},{"code":"AM:Aygezard:1","name":"Aygezard","originalName":"Aygezard"},{"code":"AM:Azatamut:1","name":"Azatamut","originalName":"Azatamut"},{"code":"AM:Azatan:1","name":"Azatan","originalName":"Azatan"},{"code":"AM:Baghramyan:1","name":"Baghramyan","originalName":"Baghramyan"},{"code":"AM:Bagratashen:1","name":"Bagratashen","originalName":"Bagratashen"},{"code":"AM:Balahovit:1","name":"Balahovit","originalName":"Balahovit"},{"code":"AM:Bambakashat:1","name":"Bambakashat","originalName":"Bambakashat"},{"code":"AM:Bardzrashen:1","name":"Bardzrashen","originalName":"Bardzrashen"},{"code":"AM:Basen:1","name":"Basen","originalName":"Basen"},{"code":"AM:Bazum:1","name":"Bazum","originalName":"Bazum"},{"code":"AM:Berd:1","name":"Berd","originalName":"Berd"},{"code":"AM:Berdavan:1","name":"Berdavan","originalName":"Berdavan"},{"code":"AM:Berk’anush:1","name":"Berk’anush","originalName":"Berk’anush"},{"code":"AM:Bjni:1","name":"Bjni","originalName":"Bjni"},{"code":"AM:Brrnakot’:1","name":"Brrnakot’","originalName":"Brrnakot’"},{"code":"AM:Burastan:1","name":"Burastan","originalName":"Burastan"},{"code":"AM:Buzhakan:1","name":"Buzhakan","originalName":"Buzhakan"},{"code":"AM:Byurakan:1","name":"Byurakan","originalName":"Byurakan"},{"code":"AM:Byuravan:1","name":"Byuravan","originalName":"Byuravan"},{"code":"AM:Byureghavan:1","name":"Byureghavan","originalName":"Byureghavan"},{"code":"AM:Chambarak:1","name":"Chambarak","originalName":"Chambarak"},{"code":"AM:Chochkan:1","name":"Chochkan","originalName":"Chochkan"},{"code":"AM:Dalar:1","name":"Dalar","originalName":"Dalar"},{"code":"AM:Dalarik:1","name":"Dalarik","originalName":"Dalarik"},{"code":"AM:Darakert:1","name":"Darakert","originalName":"Darakert"},{"code":"AM:Darpas:1","name":"Darpas","originalName":"Darpas"},{"code":"AM:Dashtavan:1","name":"Dashtavan","originalName":"Dashtavan"},{"code":"AM:Ddmashen:1","name":"Ddmashen","originalName":"Ddmashen"},{"code":"AM:Dilijan:1","name":"Dilijan","originalName":"Dilijan"},{"code":"AM:Dimitrov:1","name":"Dimitrov","originalName":"Dimitrov"},{"code":"AM:Doghs:1","name":"Doghs","originalName":"Doghs"},{"code":"AM:Drakhtik:1","name":"Drakhtik","originalName":"Drakhtik"},{"code":"AM:Dsegh:1","name":"Dsegh","originalName":"Dsegh"},{"code":"AM:Dvin:1","name":"Dvin","originalName":"Dvin"},{"code":"AM:Dzit’hank’ov:1","name":"Dzit’hank’ov","originalName":"Dzit’hank’ov"},{"code":"AM:Dzoraghbyur:1","name":"Dzoraghbyur","originalName":"Dzoraghbyur"},{"code":"AM:Dzoragyugh:1","name":"Dzoragyugh","originalName":"Dzoragyugh"},{"code":"AM:Dzorastan:1","name":"Dzorastan","originalName":"Dzorastan"},{"code":"AM:Fantan:1","name":"Fantan","originalName":"Fantan"},{"code":"AM:Fioletovo:1","name":"Fioletovo","originalName":"Fioletovo"},{"code":"AM:Gagarin:1","name":"Gagarin","originalName":"Gagarin"},{"code":"AM:Gandzak:1","name":"Gandzak","originalName":"Gandzak"},{"code":"AM:Garrni:1","name":"Garrni","originalName":"Garrni"},{"code":"AM:Gavarr:1","name":"Gavarr","originalName":"Gavarr"},{"code":"AM:Gay:1","name":"Gay","originalName":"Gay"},{"code":"AM:Geghakert:1","name":"Geghakert","originalName":"Geghakert"},{"code":"AM:Geghamasar:1","name":"Geghamasar","originalName":"Geghamasar"},{"code":"AM:Geghamavan:1","name":"Geghamavan","originalName":"Geghamavan"},{"code":"AM:Geghanist:1","name":"Geghanist","originalName":"Geghanist"},{"code":"AM:Getap’:1","name":"Getap’","originalName":"Getap’"},{"code":"AM:Getashen:1","name":"Getashen","originalName":"Getashen"},{"code":"AM:Getazat:1","name":"Getazat","originalName":"Getazat"},{"code":"AM:Ghukasavan:1","name":"Ghukasavan","originalName":"Ghukasavan"},{"code":"AM:Gladzor:1","name":"Gladzor","originalName":"Gladzor"},{"code":"AM:Gmbet’:1","name":"Gmbet’","originalName":"Gmbet’"},{"code":"AM:Gogaran:1","name":"Gogaran","originalName":"Gogaran"},{"code":"AM:Goght’:1","name":"Goght’","originalName":"Goght’"},{"code":"AM:Goravan:1","name":"Goravan","originalName":"Goravan"},{"code":"AM:Goris:1","name":"Goris","originalName":"Goris"},{"code":"AM:Griboyedov:1","name":"Griboyedov","originalName":"Griboyedov"},{"code":"AM:Gugark’:1","name":"Gugark’","originalName":"Gugark’"},{"code":"AM:Gyulagarak:1","name":"Gyulagarak","originalName":"Gyulagarak"},{"code":"AM:Gyumri:1","name":"Gyumri","originalName":"Gyumri"},{"code":"AM:Haghartsin:1","name":"Haghartsin","originalName":"Haghartsin"},{"code":"AM:Hats’avan:1","name":"Hats’avan","originalName":"Hats’avan"},{"code":"AM:Hayanist:1","name":"Hayanist","originalName":"Hayanist"},{"code":"AM:Haykashen:1","name":"Haykashen","originalName":"Haykashen"},{"code":"AM:Haykavan:1","name":"Haykavan","originalName":"Haykavan"},{"code":"AM:Hnaberd:1","name":"Hnaberd","originalName":"Hnaberd"},{"code":"AM:Horrom:1","name":"Horrom","originalName":"Horrom"},{"code":"AM:Hovtamej:1","name":"Hovtamej","originalName":"Hovtamej"},{"code":"AM:Hovtashat:1","name":"Hovtashat","originalName":"Hovtashat"},{"code":"AM:Hovtashen:1","name":"Hovtashen","originalName":"Hovtashen"},{"code":"AM:Hrazdan:1","name":"Hrazdan","originalName":"Hrazdan"},{"code":"AM:Ijevan:1","name":"Ijevan","originalName":"Ijevan"},{"code":"AM:Janfida:1","name":"Janfida","originalName":"Janfida"},{"code":"AM:Jermuk:1","name":"Jermuk","originalName":"Jermuk"},{"code":"AM:Jrahovit:1","name":"Jrahovit","originalName":"Jrahovit"},{"code":"AM:Jrashen:1","name":"Jrashen","originalName":"Jrashen"},{"code":"AM:K’anak’erravan:1","name":"K’anak’erravan","originalName":"K’anak’erravan"},{"code":"AM:Kamo:1","name":"Kamo","originalName":"Kamo"},{"code":"AM:Kapan:1","name":"Kapan","originalName":"Kapan"},{"code":"AM:Kaputan:1","name":"Kaputan","originalName":"Kaputan"},{"code":"AM:Karanlukh:1","name":"Karanlukh","originalName":"Karanlukh"},{"code":"AM:Karbi:1","name":"Karbi","originalName":"Karbi"},{"code":"AM:Karchaghbyur:1","name":"Karchaghbyur","originalName":"Karchaghbyur"},{"code":"AM:Kasakh:1","name":"Kasakh","originalName":"Kasakh"},{"code":"AM:Khasht’arrak:1","name":"Khasht’arrak","originalName":"Khasht’arrak"},{"code":"AM:Khndzoresk:1","name":"Khndzoresk","originalName":"Khndzoresk"},{"code":"AM:Khoronk’:1","name":"Khoronk’","originalName":"Khoronk’"},{"code":"AM:Kosh:1","name":"Kosh","originalName":"Kosh"},{"code":"AM:Kotayk’:1","name":"Kotayk’","originalName":"Kotayk’"},{"code":"AM:Lanjaghbyur:1","name":"Lanjaghbyur","originalName":"Lanjaghbyur"},{"code":"AM:Lchap’:1","name":"Lchap’","originalName":"Lchap’"},{"code":"AM:Lchashen:1","name":"Lchashen","originalName":"Lchashen"},{"code":"AM:Lenughi:1","name":"Lenughi","originalName":"Lenughi"},{"code":"AM:Lerrnakert:1","name":"Lerrnakert","originalName":"Lerrnakert"},{"code":"AM:Lerrnanist:1","name":"Lerrnanist","originalName":"Lerrnanist"},{"code":"AM:Lerrnants’k’:1","name":"Lerrnants’k’","originalName":"Lerrnants’k’"},{"code":"AM:Lerrnapat:1","name":"Lerrnapat","originalName":"Lerrnapat"},{"code":"AM:Lerrnavan:1","name":"Lerrnavan","originalName":"Lerrnavan"},{"code":"AM:Lichk’:1","name":"Lichk’","originalName":"Lichk’"},{"code":"AM:Lorut:1","name":"Lorut","originalName":"Lorut"},{"code":"AM:Lukashin:1","name":"Lukashin","originalName":"Lukashin"},{"code":"AM:Lusarrat:1","name":"Lusarrat","originalName":"Lusarrat"},{"code":"AM:Madina:1","name":"Madina","originalName":"Madina"},{"code":"AM:Malishka:1","name":"Malishka","originalName":"Malishka"},{"code":"AM:Maralik:1","name":"Maralik","originalName":"Maralik"},{"code":"AM:Margahovit:1","name":"Margahovit","originalName":"Margahovit"},{"code":"AM:Margara:1","name":"Margara","originalName":"Margara"},{"code":"AM:Marmarashen:1","name":"Marmarashen","originalName":"Marmarashen"},{"code":"AM:Marmashen:1","name":"Marmashen","originalName":"Marmashen"},{"code":"AM:Martuni:1","name":"Martuni","originalName":"Martuni"},{"code":"AM:Masis:1","name":"Masis","originalName":"Masis"},{"code":"AM:Mayakovski:1","name":"Mayakovski","originalName":"Mayakovski"},{"code":"AM:Mayisyan:1","name":"Mayisyan","originalName":"Mayisyan"},{"code":"AM:Meghradzor:1","name":"Meghradzor","originalName":"Meghradzor"},{"code":"AM:Meghrashen:1","name":"Meghrashen","originalName":"Meghrashen"},{"code":"AM:Meghri:1","name":"Meghri","originalName":"Meghri"},{"code":"AM:Merdzavan:1","name":"Merdzavan","originalName":"Merdzavan"},{"code":"AM:Mets Mant’ash:1","name":"Mets Mant’ash","originalName":"Mets Mant’ash"},{"code":"AM:Mets Masrik:1","name":"Mets Masrik","originalName":"Mets Masrik"},{"code":"AM:Mets Parni:1","name":"Mets Parni","originalName":"Mets Parni"},{"code":"AM:Metsamor:1","name":"Metsamor","originalName":"Metsamor"},{"code":"AM:Metsavan:1","name":"Metsavan","originalName":"Metsavan"},{"code":"AM:Mosesgegh:1","name":"Mosesgegh","originalName":"Mosesgegh"},{"code":"AM:Mrganush:1","name":"Mrganush","originalName":"Mrganush"},{"code":"AM:Mrgashat:1","name":"Mrgashat","originalName":"Mrgashat"},{"code":"AM:Mrgashen:1","name":"Mrgashen","originalName":"Mrgashen"},{"code":"AM:Mrgavan:1","name":"Mrgavan","originalName":"Mrgavan"},{"code":"AM:Mrgavet:1","name":"Mrgavet","originalName":"Mrgavet"},{"code":"AM:Musalerr:1","name":"Musalerr","originalName":"Musalerr"},{"code":"AM:Myasnikyan:1","name":"Myasnikyan","originalName":"Myasnikyan"},{"code":"AM:Nalbandyan:1","name":"Nalbandyan","originalName":"Nalbandyan"},{"code":"AM:Navur:1","name":"Navur","originalName":"Navur"},{"code":"AM:Nerk’in Getashen:1","name":"Nerk’in Getashen","originalName":"Nerk’in Getashen"},{"code":"AM:Nizami:1","name":"Nizami","originalName":"Nizami"},{"code":"AM:Nor Armavir:1","name":"Nor Armavir","originalName":"Nor Armavir"},{"code":"AM:Nor Geghi:1","name":"Nor Geghi","originalName":"Nor Geghi"},{"code":"AM:Nor Gyugh:1","name":"Nor Gyugh","originalName":"Nor Gyugh"},{"code":"AM:Nor Yerznka:1","name":"Nor Yerznka","originalName":"Nor Yerznka"},{"code":"AM:Norabats’:1","name":"Norabats’","originalName":"Norabats’"},{"code":"AM:Norakert:1","name":"Norakert","originalName":"Norakert"},{"code":"AM:Noramarg:1","name":"Noramarg","originalName":"Noramarg"},{"code":"AM:Norashen:1","name":"Norashen","originalName":"Norashen"},{"code":"AM:Noratus:1","name":"Noratus","originalName":"Noratus"},{"code":"AM:Noyakert:1","name":"Noyakert","originalName":"Noyakert"},{"code":"AM:Noyemberyan:1","name":"Noyemberyan","originalName":"Noyemberyan"},{"code":"AM:Nshavan:1","name":"Nshavan","originalName":"Nshavan"},{"code":"AM:Odzun:1","name":"Odzun","originalName":"Odzun"},{"code":"AM:Oshakan:1","name":"Oshakan","originalName":"Oshakan"},{"code":"AM:P’ok’r Mant’ash:1","name":"P’ok’r Mant’ash","originalName":"P’ok’r Mant’ash"},{"code":"AM:P’shatavan:1","name":"P’shatavan","originalName":"P’shatavan"},{"code":"AM:Parravak’ar:1","name":"Parravak’ar","originalName":"Parravak’ar"},{"code":"AM:Pemzashen:1","name":"Pemzashen","originalName":"Pemzashen"},{"code":"AM:Prroshyan:1","name":"Prroshyan","originalName":"Prroshyan"},{"code":"AM:Ptghni:1","name":"Ptghni","originalName":"Ptghni"},{"code":"AM:Ptghunk’:1","name":"Ptghunk’","originalName":"Ptghunk’"},{"code":"AM:Rrind:1","name":"Rrind","originalName":"Rrind"},{"code":"AM:Sarahart’:1","name":"Sarahart’","originalName":"Sarahart’"},{"code":"AM:Saramej:1","name":"Saramej","originalName":"Saramej"},{"code":"AM:Saratak:1","name":"Saratak","originalName":"Saratak"},{"code":"AM:Sardarapat:1","name":"Sardarapat","originalName":"Sardarapat"},{"code":"AM:Sarigyugh:1","name":"Sarigyugh","originalName":"Sarigyugh"},{"code":"AM:Sarukhan:1","name":"Sarukhan","originalName":"Sarukhan"},{"code":"AM:Sasunik:1","name":"Sasunik","originalName":"Sasunik"},{"code":"AM:Sayat’-Nova:1","name":"Sayat’-Nova","originalName":"Sayat’-Nova"},{"code":"AM:Sevan:1","name":"Sevan","originalName":"Sevan"},{"code":"AM:Shaghat:1","name":"Shaghat","originalName":"Shaghat"},{"code":"AM:Shahumyan:1","name":"Shahumyan","originalName":"Shahumyan"},{"code":"AM:Shatin:1","name":"Shatin","originalName":"Shatin"},{"code":"AM:Shenavan:1","name":"Shenavan","originalName":"Shenavan"},{"code":"AM:Shinuhayr:1","name":"Shinuhayr","originalName":"Shinuhayr"},{"code":"AM:Shirak:1","name":"Shirak","originalName":"Shirak"},{"code":"AM:Shirakamut:1","name":"Shirakamut","originalName":"Shirakamut"},{"code":"AM:Shnogh:1","name":"Shnogh","originalName":"Shnogh"},{"code":"AM:Sis:1","name":"Sis","originalName":"Sis"},{"code":"AM:Sisavan:1","name":"Sisavan","originalName":"Sisavan"},{"code":"AM:Solak:1","name":"Solak","originalName":"Solak"},{"code":"AM:Spandaryan:1","name":"Spandaryan","originalName":"Spandaryan"},{"code":"AM:Spitak:1","name":"Spitak","originalName":"Spitak"},{"code":"AM:Step’anavan:1","name":"Step’anavan","originalName":"Step’anavan"},{"code":"AM:Surenavan:1","name":"Surenavan","originalName":"Surenavan"},{"code":"AM:T’alin:1","name":"T’alin","originalName":"T’alin"},{"code":"AM:Tandzut:1","name":"Tandzut","originalName":"Tandzut"},{"code":"AM:Taronik:1","name":"Taronik","originalName":"Taronik"},{"code":"AM:Tashir:1","name":"Tashir","originalName":"Tashir"},{"code":"AM:Tegh:1","name":"Tegh","originalName":"Tegh"},{"code":"AM:Tsaghkaber:1","name":"Tsaghkaber","originalName":"Tsaghkaber"},{"code":"AM:Tsaghkadzor:1","name":"Tsaghkadzor","originalName":"Tsaghkadzor"},{"code":"AM:Tsaghkahovit:1","name":"Tsaghkahovit","originalName":"Tsaghkahovit"},{"code":"AM:Tsaghkunk’:1","name":"Tsaghkunk’","originalName":"Tsaghkunk’"},{"code":"AM:Tsiatsan:1","name":"Tsiatsan","originalName":"Tsiatsan"},{"code":"AM:Tsovagyugh:1","name":"Tsovagyugh","originalName":"Tsovagyugh"},{"code":"AM:Tsovak:1","name":"Tsovak","originalName":"Tsovak"},{"code":"AM:Tsovasar:1","name":"Tsovasar","originalName":"Tsovasar"},{"code":"AM:Tsovazard:1","name":"Tsovazard","originalName":"Tsovazard"},{"code":"AM:Tsovinar:1","name":"Tsovinar","originalName":"Tsovinar"},{"code":"AM:Urrut:1","name":"Urrut","originalName":"Urrut"},{"code":"AM:Ushi:1","name":"Ushi","originalName":"Ushi"},{"code":"AM:Vagharshapat:1","name":"Vagharshapat","originalName":"Vagharshapat"},{"code":"AM:Vaghashen:1","name":"Vaghashen","originalName":"Vaghashen"},{"code":"AM:Vahagni:1","name":"Vahagni","originalName":"Vahagni"},{"code":"AM:Vahan:1","name":"Vahan","originalName":"Vahan"},{"code":"AM:Vanadzor:1","name":"Vanadzor","originalName":"Vanadzor"},{"code":"AM:Vardablur:1","name":"Vardablur","originalName":"Vardablur"},{"code":"AM:Vardadzor:1","name":"Vardadzor","originalName":"Vardadzor"},{"code":"AM:Vardenik:1","name":"Vardenik","originalName":"Vardenik"},{"code":"AM:Vardenis:1","name":"Vardenis","originalName":"Vardenis"},{"code":"AM:Varser:1","name":"Varser","originalName":"Varser"},{"code":"AM:Vayk’:1","name":"Vayk’","originalName":"Vayk’"},{"code":"AM:Vedi:1","name":"Vedi","originalName":"Vedi"},{"code":"AM:Verin Artashat:1","name":"Verin Artashat","originalName":"Verin Artashat"},{"code":"AM:Verin Dvin:1","name":"Verin Dvin","originalName":"Verin Dvin"},{"code":"AM:Verin Getashen:1","name":"Verin Getashen","originalName":"Verin Getashen"},{"code":"AM:Verishen:1","name":"Verishen","originalName":"Verishen"},{"code":"AM:Vernashen:1","name":"Vernashen","originalName":"Vernashen"},{"code":"AM:Voskehask:1","name":"Voskehask","originalName":"Voskehask"},{"code":"AM:Voskehat:1","name":"Voskehat","originalName":"Voskehat"},{"code":"AM:Vosketap’:1","name":"Vosketap’","originalName":"Vosketap’"},{"code":"AM:Voskevan:1","name":"Voskevan","originalName":"Voskevan"},{"code":"AM:Voskevaz:1","name":"Voskevaz","originalName":"Voskevaz"},{"code":"AM:Vostan:1","name":"Vostan","originalName":"Vostan"},{"code":"AM:Yeghegis:1","name":"Yeghegis","originalName":"Yeghegis"},{"code":"AM:Yeghegnadzor:1","name":"Yeghegnadzor","originalName":"Yeghegnadzor"},{"code":"AM:Yeghegnavan:1","name":"Yeghegnavan","originalName":"Yeghegnavan"},{"code":"AM:Yeghegnut:1","name":"Yeghegnut","originalName":"Yeghegnut"},{"code":"AM:Yeghvard:1","name":"Yeghvard","originalName":"Yeghvard"},{"code":"AM:Yeranos:1","name":"Yeranos","originalName":"Yeranos"},{"code":"AM:Yeraskhahun:1","name":"Yeraskhahun","originalName":"Yeraskhahun"},{"code":"AM:Yerazgavors:1","name":"Yerazgavors","originalName":"Yerazgavors"},{"code":"AM:Yerevan:1","name":"Yerevan","originalName":"Yerevan"},{"code":"AM:Zangakatun:1","name":"Zangakatun","originalName":"Zangakatun"},{"code":"AM:Zarr:1","name":"Zarr","originalName":"Zarr"},{"code":"AM:Zarrit’ap’:1","name":"Zarrit’ap’","originalName":"Zarrit’ap’"},{"code":"AM:Zorak:1","name":"Zorak","originalName":"Zorak"},{"code":"AM:Zoravan:1","name":"Zoravan","originalName":"Zoravan"},{"code":"AM:Zovaber:1","name":"Zovaber","originalName":"Zovaber"},{"code":"AM:Zovuni:1","name":"Zovuni","originalName":"Zovuni"}]
