[{"code":"TT:Arima:1","name":"Arima","originalName":"Arima"},{"code":"TT:Arouca:1","name":"Arouca","originalName":"Arouca"},{"code":"TT:Chaguanas:1","name":"Chaguanas","originalName":"Chaguanas"},{"code":"TT:Couva:1","name":"Couva","originalName":"Couva"},{"code":"TT:Debe:1","name":"Debe","originalName":"Debe"},{"code":"TT:Laventille:1","name":"Laventille","originalName":"Laventille"},{"code":"TT:Marabella:1","name":"Marabella","originalName":"Marabella"},{"code":"TT:Mon Repos:1","name":"Mon Repos","originalName":"Mon Repos"},{"code":"TT:Mucurapo:1","name":"Mucurapo","originalName":"Mucurapo"},{"code":"TT:Paradise:1","name":"Paradise","originalName":"Paradise"},{"code":"TT:Peñal:1","name":"Peñal","originalName":"Peñal"},{"code":"TT:Petit Valley:1","name":"Petit Valley","originalName":"Petit Valley"},{"code":"TT:Point Fortin:1","name":"Point Fortin","originalName":"Point Fortin"},{"code":"TT:Port of Spain:1","name":"Port of Spain","originalName":"Port of Spain"},{"code":"TT:Princes Town:1","name":"Princes Town","originalName":"Princes Town"},{"code":"TT:Rio Claro:1","name":"Rio Claro","originalName":"Rio Claro"},{"code":"TT:San Fernando:1","name":"San Fernando","originalName":"San Fernando"},{"code":"TT:Sangre Grande:1","name":"Sangre Grande","originalName":"Sangre Grande"},{"code":"TT:Scarborough:1","name":"Scarborough","originalName":"Scarborough"},{"code":"TT:Siparia:1","name":"Siparia","originalName":"Siparia"},{"code":"TT:Tabaquite:1","name":"Tabaquite","originalName":"Tabaquite"},{"code":"TT:Tunapuna:1","name":"Tunapuna","originalName":"Tunapuna"},{"code":"TT:Ward of Chaguanas:1","name":"Ward of Chaguanas","originalName":"Ward of Chaguanas"},{"code":"TT:Ward of Diego Martin:1","name":"Ward of Diego Martin","originalName":"Ward of Diego Martin"},{"code":"TT:Ward of Siparia:1","name":"Ward of Siparia","originalName":"Ward of Siparia"}]
